signle_clk_cpu/defines.v

// common define
`define datawidth                           32
`define RstEnable                           1'b0
`define RstDisable                          1'b1
`define ZeroWord                            32'd0
`define ZeroReg                             5'd0
//instr_RAM
`define addrwidth                           8
//ALU
`define ALU_CLT                             3:0
`define SHIFT_NUM_width                     4:0
`define shift_ctr                           1:0
//diver
`define DIV_STEPS                           32
`define DIV_STEPS_Log2                      6
//*************
`define CpuResetAddr                        32'h0


`define WriteEnable                         1'b1
`define WriteDisable                        1'b0
`define ReadEnable                          1'b1
`define ReadDisable                         1'b0
`define True                                1'b1
`define False                               1'b0
`define ChipEnable                          1'b1
`define ChipDisable                         1'b0
`define JumpEnable                          1'b1
`define JumpDisable                         1'b0
`define DivResultNotReady                   1'b0
`define DivResultReady                      1'b1
`define DivStart                            1'b1
`define DivStop                             1'b0
`define HoldEnable                          1'b1
`define HoldDisable                         1'b0
`define Stop                                1'b1
`define NoStop                              1'b0
`define RIB_ACK                             1'b1
`define RIB_NACK                            1'b0
`define RIB_REQ                             1'b1
`define RIB_NREQ                            1'b0
`define INT_ASSERT                          1'b1
`define INT_DEASSERT                        1'b0

`define INT_BUS                             7:0
`define INT_NONE                            8'h0
`define INT_RET                             8'hff
`define INT_TIMER0                          8'b00000001
`define INT_TIMER0_ENTRY_ADDR               32'h4

`define Hold_Flag_Bus                       2:0
`define Hold_None                           3'b000
`define Hold_Pc                             3'b001
`define Hold_If                             3'b010
`define Hold_Id                             3'b011

// I type inst
`define I_TYPE                              7'b0010011
`define INST_ADDI                           3'b000
`define INST_SLTI                           3'b010
`define INST_SLTIU                          3'b011
`define INST_XORI                           3'b100
`define INST_ORI                            3'b110
`define INST_ANDI                           3'b111
`define INST_SLLI                           3'b001
`define INST_SRI                            3'b101



// L type inst
`define L_TYPE                              7'b0000011
`define INST_LB                             3'b000
`define INST_LH                             3'b001
`define INST_LW                             3'b010
`define INST_LBU                            3'b100
`define INST_LHU                            3'b101
`define lb  			                    3'b000
`define lh  			                    3'b010
`define lw		                            3'b011
`define lbu  			                    3'b100
`define lhu  			                    3'b110


// S type inst
`define S_TYPE                              7'b0100011
`define sb  			                    3'b000
`define sh  			                    3'b001
`define sw  			                    3'b010

// R and M type inst
`define R_TYPE                              7'b0110011
// R type inst
`define INST_ADD_SUB                        3'b000
`define INST_SLL                            3'b001
`define INST_SLT                            3'b010
`define INST_SLTU                           3'b011
`define INST_XOR                            3'b100
`define INST_SR                             3'b101
`define INST_OR                             3'b110
`define INST_AND                            3'b111
// M type inst
`define INST_MUL                            3'b000
`define INST_MULH                           3'b001
`define INST_MULHSU                         3'b010
`define INST_MULHU                          3'b011
`define INST_DIV                            3'b100
`define INST_DIVU                           3'b101
`define INST_REM                            3'b110
`define INST_REMU                           3'b111

// J type inst
`define INST_JAL                            7'b1101111
`define INST_JALR                           7'b1100111
//U type inst
`define INST_LUI                            7'b0110111
`define INST_AUIPC                          7'b0010111


`define INST_NOP                            32'h00000001
`define INST_NOP_OP                         7'b0000001
`define INST_MRET                           32'h30200073
`define INST_RET                            32'h0000
`define INST_FENCE                          7'b0001111
`define INST_ECALL                          32'h73
`define INST_EBREAK                         32'h00100073

// B type inst
`define B_TYPE                              7'b1100011
`define INST_BEQ                            3'b000
`define INST_BNE                            3'b001
`define INST_BLT                            3'b100
`define INST_BGE                            3'b101
`define INST_BLTU                           3'b110
`define INST_BGEU                           3'b111

// CSR inst
`define CSR_TYPE                            7'b1110011
`define INST_CSRRW                          3'b001
`define INST_CSRRS                          3'b010
`define INST_CSRRC                          3'b011
`define INST_CSRRWI                         3'b101
`define INST_CSRRSI                         3'b110
`define INST_CSRRCI                         3'b111
// FENCE inst
`define FENCE_TYPE                          7'b0001111        
// CSR reg addr
`define CSR_CYCLE                           12'hc00
`define CSR_CYCLEH                          12'hc80
`define CSR_MTVEC                           12'h305
`define CSR_MCAUSE                          12'h342
`define CSR_MEPC                            12'h341
`define CSR_MIE                             12'h304
`define CSR_MSTATUS                         12'h300
`define CSR_MSCRATCH                        12'h340

`define RomNum                              4096  // rom depth(how many words)

`define MemNum                              4096  // memory depth(how many words)
`define MemBus                              31:0
`define MemAddrBus                          31:0

`define InstBus                             31:0
`define InstAddrBus                         31:0

// common regs
`define RegAddrBus                          4:0
`define RegBus                              31:0
`define DoubleRegBus                        63:0
`define RegWidth                            32
`define RegNum                              32        // reg num
`define RegNumLog2                          5


//saturating_counter
`define strong_not_taken                    2'b00
`define weakly_not_taken                    2'b01
`define weakly_taken                        2'b10
`define strong_taken                        2'b11

pipeline_cpu/adder.v
`timescale 1ns / 1ps
`include "defines.v"
//////////////////////////////////////////////////////////////////////////////////
// Company: 
// Engineer: 
// 
// Create Date: 2022/04/19 16:22:20
// Design Name: 
// Module Name: adder
// Project Name: 
// Target Devices: 
// Tool Versions: 
// Description: 
// 
// Dependencies: 
// 
// Revision:
// Revision 0.01 - File Created
// Additional Comments:
// 
//////////////////////////////////////////////////////////////////////////////////


module adder(
    input [`datawidth-1:0] data_A,data_B,
    input ci,
    output [`datawidth-1:0] result,
    output co,zero,result_sign,overflow
    );
    assign {co,result}=data_A+data_B+ci;
    assign overflow = data_A[`datawidth-1]&data_B[`datawidth-1]&(~result[`datawidth-1])|(~data_A[`datawidth-1])&(~data_B[`datawidth-1])&result[`datawidth-1];
    assign zero = ~(|result);
    assign result_sign=result[`datawidth-1];
endmodule

pipeline_cpu/uint_diver.v
`timescale 1ns / 1ps
`include "defines.v"
`include "adder.v"
module uint_diver (
input diver_en,
input clk,
input  [`datawidth-1:0] dividend,divisor,
output [`datawidth-1:0] remainder,
output [`datawidth-1:0] result,
output end_flag
);
reg diver_en_temp;
always @(posedge clk ) begin
    diver_en_temp <= diver_en;
end
//count
reg [`DIV_STEPS_Log2-1:0] cnt;
wire cnt_start,cnt_end;
// diver
reg  [`datawidth-1:0]  data_B;
reg [`datawidth*2-1:0] temp_A;
reg  [`datawidth-1:0]  remainder_reg, result_ci ;
wire [`datawidth-1:0]  add_result,data_A,n_data_B;
wire [`datawidth*2-1:0] temp_A_shift;
wire co;

always @(posedge clk ) begin

       if (!diver_en_temp)begin
           cnt<=0;
           end
        else if (cnt_start)
            begin
                 if (cnt_end)
                     cnt<=0;
                 else
                     cnt<=cnt+1;
            end
        else   cnt<=0 ;
end
assign cnt_start = diver_en_temp ;
assign cnt_end = cnt_start& (cnt == `DIV_STEPS);//计算需要32个时钟,数据加载1个时钟，总共33个时钟

assign temp_A_shift = temp_A << 1 ;
assign n_data_B = ~ data_B;
assign data_A = temp_A_shift[63:32];
// always @ ( posedge clk  )begin
//     if (diver_en) begin
//         if (cnt == 0) begin
//             data_B <= divisor ;
//             temp_A <= {32'd0,dividend};
//         end
//         else if ( co )begin
//             temp_A <= {add_result,temp_A_shift[31:1],1'b1};
//         end
//         else temp_A <= temp_A_shift;
//     end
//     else temp_A<=temp_A;
        

// end
always @ ( posedge clk  )begin
    if (diver_en_temp) begin
        if ( co )begin
            temp_A <= {add_result,temp_A_shift[31:1],1'b1};
        end
        else temp_A <= temp_A_shift;
        
    end       
    else begin
        data_B <= divisor ;
        temp_A <= {32'd0,dividend};
    end
        
    end
        


assign remainder      =  temp_A[63:32];
assign result      =  temp_A[31:0];


//加法器只执行减法操作，即对数据B进行取反，进位输入置1，从而达到加上补码的功能。
adder u_adder(.data_A      ( data_A      ),.data_B      ( n_data_B    ),.ci          ( 1'b1        ),.result      ( add_result  ),.co          ( co          )//无符号减法，进位输出为0时发生借位
);
//wire end_flag_temp;
assign end_flag = cnt_end ; 
// always @(posedge clk ) begin
//     end_flag <= end_flag_temp;
// end

endmodule //u_diver

pipeline_cpu/int_driver.v
`timescale 1ns / 1ps
`include "uint_diver.v"
module int_driver (
    input  clk,
    //input  rst_n,
    input diver_en,
    input  sign_flag,//为1时：无符号运算
    input  [`datawidth-1:0] dividend,divisor, 
    output [`datawidth-1:0] remainder,
    output [`datawidth-1:0] result,
    output end_flag
);
wire [`datawidth-1:0] dividend_temp,divisor_temp;
wire [`datawidth-1:0] remainder_temp,result_temp;
assign dividend_temp = sign_flag ? dividend : dividend [`datawidth-1] ? {1'b0,~dividend[`datawidth-2:0]}+1'b1:dividend;
assign divisor_temp = sign_flag ? divisor : divisor [`datawidth-1] ? {1'b0,~divisor[`datawidth-2:0]}+1'b1:divisor;
uint_diver u_uint_diver(
    .diver_en  ( diver_en  ),
    .clk       ( clk       ),
    //.rst_n     ( rst_n     ),
    .dividend  ( dividend_temp  ),
    .divisor   ( divisor_temp   ),
    .remainder ( remainder_temp ),
    .result    ( result_temp    ),
    .end_flag  ( end_flag  )
);
assign remainder =sign_flag ? remainder_temp : dividend [`datawidth-1]^divisor [`datawidth-1] ? ~remainder_temp[`datawidth-2:0]+1'b1 : remainder_temp;
assign result =sign_flag ? result_temp : dividend [`datawidth-1]^divisor [`datawidth-1] ? ~result_temp[`datawidth-2:0]+1'b1 : result_temp;

endmodule //int_driver

pipeline_cpu/tb_int_driver.v
`timescale  1ns / 1ps   
`include "int_driver.v"
module tb_int_driver;   

// int_driver Parameters
parameter PERIOD  = 10;


// int_driver Inputs
reg   clk                                  = 0 ;
reg   rst_n                                = 0 ;
reg   diver_en                             = 0 ;
reg   sign_flag                            = 0 ;
reg   [`datawidth-1:0]  dividend           = 0 ;
reg   [`datawidth-1:0]  divisor            = 0 ;

// int_driver Outputs
wire  [`datawidth-1:0]  remainder          ;
wire  [`datawidth-1:0]  result             ;
wire  end_flag                             ;


initial
begin
    forever #(PERIOD/2)  clk=~clk;
end

// initial
// begin
//     #(PERIOD*2) rst_n  =  1;
// end

int_driver  u_int_driver (
    .clk                     ( clk                         ),
    //.rst_n                   ( rst_n                       ),
    .diver_en                ( diver_en                    ),
    .sign_flag               ( sign_flag                   ),
    .dividend                ( dividend   [`datawidth-1:0] ),
    .divisor                 ( divisor    [`datawidth-1:0] ),

    .remainder               ( remainder  [`datawidth-1:0] ),
    .result                  ( result     [`datawidth-1:0] ),
    .end_flag                ( end_flag                    )
);

initial
begin
    $dumpfile("int_diver_wave.vcd");
    $dumpvars    ;
    diver_en=1;
    sign_flag=0;
    dividend = 32'b1111_1111_1111_1111_1111_1111_1111_1001;
    divisor  = 32'b1111_1111_1111_1111_1111_1111_1111_1100;
    #330
    diver_en=0;
    #10
    diver_en=1;
    sign_flag=1;
    #330
    diver_en=0;
    #10
    diver_en=1;
    sign_flag=0;
    dividend = 32'b1111_1111_1111_1111_1111_1111_1111_1111;
    divisor  = 32'b0000_0000_0000_0000_0000_0000_0000_0011;
    #330
    diver_en=0;
    #10
    diver_en=1;
    sign_flag=1;
    #330
    diver_en=0;
    #100
    $finish;
end

endmodule

pipeline_cpu/int_diver_wave.vcd
$date
	Mon May 09 18:37:32 2022
$end
$version
	Icarus Verilog
$end
$timescale
	1ps
$end
$scope module tb_int_driver $end
$var wire 32 ! result [31:0] $end
$var wire 32 " remainder [31:0] $end
$var wire 1 # end_flag $end
$var reg 1 $ clk $end
$var reg 1 % diver_en $end
$var reg 32 & dividend [31:0] $end
$var reg 32 ' divisor [31:0] $end
$var reg 1 ( rst_n $end
$var reg 1 ) sign_flag $end
$scope module u_int_driver $end
$var wire 1 $ clk $end
$var wire 1 % diver_en $end
$var wire 32 * dividend [31:0] $end
$var wire 32 + divisor [31:0] $end
$var wire 1 ) sign_flag $end
$var wire 32 , result_temp [31:0] $end
$var wire 32 - result [31:0] $end
$var wire 32 . remainder_temp [31:0] $end
$var wire 32 / remainder [31:0] $end
$var wire 1 # end_flag $end
$var wire 32 0 divisor_temp [31:0] $end
$var wire 32 1 dividend_temp [31:0] $end
$scope module u_uint_diver $end
$var wire 1 $ clk $end
$var wire 1 2 cnt_end $end
$var wire 1 % diver_en $end
$var wire 32 3 dividend [31:0] $end
$var wire 32 4 divisor [31:0] $end
$var wire 1 # end_flag $end
$var wire 32 5 n_data_B [31:0] $end
$var wire 64 6 temp_A_shift [63:0] $end
$var wire 32 7 result [31:0] $end
$var wire 32 8 remainder [31:0] $end
$var wire 32 9 data_A [31:0] $end
$var wire 1 : co $end
$var wire 1 ; cnt_start $end
$var wire 32 < add_result [31:0] $end
$var reg 6 = cnt [5:0] $end
$var reg 32 > data_B [31:0] $end
$var reg 1 ; diver_en_temp $end
$var reg 64 ? temp_A [63:0] $end
$scope module u_adder $end
$var wire 1 @ ci $end
$var wire 32 A data_A [31:0] $end
$var wire 32 B data_B [31:0] $end
$var wire 1 C overflow $end
$var wire 1 D zero $end
$var wire 1 E result_sign $end
$var wire 32 F result [31:0] $end
$var wire 1 : co $end
$upscope $end
$upscope $end
$upscope $end
$upscope $end
$enddefinitions $end
#0
$dumpvars
bx F
xE
xD
xC
bx B
bx A
1@
bx ?
bx >
bx =
bx <
x;
x:
bx 9
bx 8
bx 7
bx0 6
bx 5
b100 4
b111 3
x2
b111 1
b100 0
bx /
bx .
bx -
bx ,
b11111111111111111111111111111100 +
b11111111111111111111111111111001 *
0)
0(
b11111111111111111111111111111100 '
b11111111111111111111111111111001 &
1%
0$
x#
bx "
bx !
$end
#5000
0C
0D
1E
b11111111111111111111111111111100 <
b11111111111111111111111111111100 F
0:
b0 "
b0 /
b111 !
b111 -
b0 9
b0 A
0#
02
b1110 6
b0 .
b0 8
b111 ,
b111 7
b11111111111111111111111111111011 5
b11111111111111111111111111111011 B
1;
b0 =
b111 ?
b100 >
1$
#10000
0$
#15000
b1110 !
b1110 -
b11100 6
b1110 ,
b1110 7
b1110 ?
b1 =
1$
#20000
0$
#25000
b11100 !
b11100 -
b111000 6
b11100 ,
b11100 7
b10 =
b11100 ?
1$
#30000
0$
#35000
b111000 !
b111000 -
b1110000 6
b111000 ,
b111000 7
b111000 ?
b11 =
1$
#40000
0$
#45000
b1110000 !
b1110000 -
b11100000 6
b1110000 ,
b1110000 7
b100 =
b1110000 ?
1$
#50000
0$
#55000
b11100000 !
b11100000 -
b111000000 6
b11100000 ,
b11100000 7
b11100000 ?
b101 =
1$
#60000
0$
#65000
b111000000 !
b111000000 -
b1110000000 6
b111000000 ,
b111000000 7
b110 =
b111000000 ?
1$
#70000
0$
#75000
b1110000000 !
b1110000000 -
b11100000000 6
b1110000000 ,
b1110000000 7
b1110000000 ?
b111 =
1$
#80000
0$
#85000
b11100000000 !
b11100000000 -
b111000000000 6
b11100000000 ,
b11100000000 7
b1000 =
b11100000000 ?
1$
#90000
0$
#95000
b111000000000 !
b111000000000 -
b1110000000000 6
b111000000000 ,
b111000000000 7
b111000000000 ?
b1001 =
1$
#100000
0$
#105000
b1110000000000 !
b1110000000000 -
b11100000000000 6
b1110000000000 ,
b1110000000000 7
b1010 =
b1110000000000 ?
1$
#110000
0$
#115000
b11100000000000 !
b11100000000000 -
b111000000000000 6
b11100000000000 ,
b11100000000000 7
b11100000000000 ?
b1011 =
1$
#120000
0$
#125000
b111000000000000 !
b111000000000000 -
b1110000000000000 6
b111000000000000 ,
b111000000000000 7
b1100 =
b111000000000000 ?
1$
#130000
0$
#135000
b1110000000000000 !
b1110000000000000 -
b11100000000000000 6
b1110000000000000 ,
b1110000000000000 7
b1110000000000000 ?
b1101 =
1$
#140000
0$
#145000
b11100000000000000 !
b11100000000000000 -
b111000000000000000 6
b11100000000000000 ,
b11100000000000000 7
b1110 =
b11100000000000000 ?
1$
#150000
0$
#155000
b111000000000000000 !
b111000000000000000 -
b1110000000000000000 6
b111000000000000000 ,
b111000000000000000 7
b111000000000000000 ?
b1111 =
1$
#160000
0$
#165000
b1110000000000000000 !
b1110000000000000000 -
b11100000000000000000 6
b1110000000000000000 ,
b1110000000000000000 7
b10000 =
b1110000000000000000 ?
1$
#170000
0$
#175000
b11100000000000000000 !
b11100000000000000000 -
b111000000000000000000 6
b11100000000000000000 ,
b11100000000000000000 7
b11100000000000000000 ?
b10001 =
1$
#180000
0$
#185000
b111000000000000000000 !
b111000000000000000000 -
b1110000000000000000000 6
b111000000000000000000 ,
b111000000000000000000 7
b10010 =
b111000000000000000000 ?
1$
#190000
0$
#195000
b1110000000000000000000 !
b1110000000000000000000 -
b11100000000000000000000 6
b1110000000000000000000 ,
b1110000000000000000000 7
b1110000000000000000000 ?
b10011 =
1$
#200000
0$
#205000
b11100000000000000000000 !
b11100000000000000000000 -
b111000000000000000000000 6
b11100000000000000000000 ,
b11100000000000000000000 7
b10100 =
b11100000000000000000000 ?
1$
#210000
0$
#215000
b111000000000000000000000 !
b111000000000000000000000 -
b1110000000000000000000000 6
b111000000000000000000000 ,
b111000000000000000000000 7
b111000000000000000000000 ?
b10101 =
1$
#220000
0$
#225000
b1110000000000000000000000 !
b1110000000000000000000000 -
b11100000000000000000000000 6
b1110000000000000000000000 ,
b1110000000000000000000000 7
b10110 =
b1110000000000000000000000 ?
1$
#230000
0$
#235000
b11100000000000000000000000 !
b11100000000000000000000000 -
b111000000000000000000000000 6
b11100000000000000000000000 ,
b11100000000000000000000000 7
b11100000000000000000000000 ?
b10111 =
1$
#240000
0$
#245000
b111000000000000000000000000 !
b111000000000000000000000000 -
b1110000000000000000000000000 6
b111000000000000000000000000 ,
b111000000000000000000000000 7
b11000 =
b111000000000000000000000000 ?
1$
#250000
0$
#255000
b1110000000000000000000000000 !
b1110000000000000000000000000 -
b11100000000000000000000000000 6
b1110000000000000000000000000 ,
b1110000000000000000000000000 7
b1110000000000000000000000000 ?
b11001 =
1$
#260000
0$
#265000
b11100000000000000000000000000 !
b11100000000000000000000000000 -
b111000000000000000000000000000 6
b11100000000000000000000000000 ,
b11100000000000000000000000000 7
b11010 =
b11100000000000000000000000000 ?
1$
#270000
0$
#275000
b111000000000000000000000000000 !
b111000000000000000000000000000 -
b1110000000000000000000000000000 6
b111000000000000000000000000000 ,
b111000000000000000000000000000 7
b111000000000000000000000000000 ?
b11011 =
1$
#280000
0$
#285000
b1110000000000000000000000000000 !
b1110000000000000000000000000000 -
b11100000000000000000000000000000 6
b1110000000000000000000000000000 ,
b1110000000000000000000000000000 7
b11100 =
b1110000000000000000000000000000 ?
1$
#290000
0$
#295000
b11111111111111111111111111111101 <
b11111111111111111111111111111101 F
b11100000000000000000000000000000 !
b11100000000000000000000000000000 -
b1 9
b1 A
b111000000000000000000000000000000 6
b11100000000000000000000000000000 ,
b11100000000000000000000000000000 7
b11100000000000000000000000000000 ?
b11101 =
1$
#300000
0$
#305000
b11111111111111111111111111111111 <
b11111111111111111111111111111111 F
b1 "
b1 /
b11000000000000000000000000000000 !
b11000000000000000000000000000000 -
b11 9
b11 A
b1110000000000000000000000000000000 6
b1 .
b1 8
b11000000000000000000000000000000 ,
b11000000000000000000000000000000 7
b11110 =
b111000000000000000000000000000000 ?
1$
#310000
0$
#315000
0E
b11 <
b11 F
1:
b11 "
b11 /
b10000000000000000000000000000000 !
b10000000000000000000000000000000 -
b111 9
b111 A
b11100000000000000000000000000000000 6
b11 .
b11 8
b10000000000000000000000000000000 ,
b10000000000000000000000000000000 7
b1110000000000000000000000000000000 ?
b11111 =
1$
#320000
0$
#325000
b10 <
b10 F
b1 !
b1 -
b110 9
b110 A
1#
12
b11000000000000000000000000000000010 6
b1 ,
b1 7
b100000 =
b1100000000000000000000000000000001 ?
1$
#330000
0$
0%
#335000
1D
b0 <
b0 F
b10 "
b10 /
b11 !
b11 -
b100 9
b100 A
b10000000000000000000000000000000110 6
b10 .
b10 8
b11 ,
b11 7
0#
02
b1000000000000000000000000000000011 ?
b0 =
0;
1$
#340000
b11111111111111111111111111111001 1
b11111111111111111111111111111001 3
b11111111111111111111111111111100 0
b11111111111111111111111111111100 4
0$
1)
1%
#345000
0D
b1 9
b1 A
b0 "
b0 /
b11111111111111111111111111111001 !
b11111111111111111111111111111001 -
b101 <
b101 F
0:
b111111111111111111111111111110010 6
b0 .
b0 8
b11111111111111111111111111111001 ,
b11111111111111111111111111111001 7
b11 5
b11 B
1;
b11111111111111111111111111111001 ?
b11111111111111111111111111111100 >
1$
#350000
0$
#355000
b111 <
b111 F
b11 9
b11 A
b1 "
b1 /
b11111111111111111111111111110010 !
b11111111111111111111111111110010 -
b1111111111111111111111111111100100 6
b1 .
b1 8
b11111111111111111111111111110010 ,
b11111111111111111111111111110010 7
b111111111111111111111111111110010 ?
b1 =
1$
#360000
0$
#365000
b1011 <
b1011 F
b111 9
b111 A
b11 "
b11 /
b11111111111111111111111111100100 !
b11111111111111111111111111100100 -
b11111111111111111111111111111001000 6
b11 .
b11 8
b11111111111111111111111111100100 ,
b11111111111111111111111111100100 7
b10 =
b1111111111111111111111111111100100 ?
1$
#370000
0$
#375000
b10011 <
b10011 F
b1111 9
b1111 A
b111 "
b111 /
b11111111111111111111111111001000 !
b11111111111111111111111111001000 -
b111111111111111111111111111110010000 6
b111 .
b111 8
b11111111111111111111111111001000 ,
b11111111111111111111111111001000 7
b11111111111111111111111111111001000 ?
b11 =
1$
#380000
0$
#385000
b100011 <
b100011 F
b11111 9
b11111 A
b1111 "
b1111 /
b11111111111111111111111110010000 !
b11111111111111111111111110010000 -
b1111111111111111111111111111100100000 6
b1111 .
b1111 8
b11111111111111111111111110010000 ,
b11111111111111111111111110010000 7
b100 =
b111111111111111111111111111110010000 ?
1$
#390000
0$
#395000
b1000011 <
b1000011 F
b111111 9
b111111 A
b11111 "
b11111 /
b11111111111111111111111100100000 !
b11111111111111111111111100100000 -
b11111111111111111111111111111001000000 6
b11111 .
b11111 8
b11111111111111111111111100100000 ,
b11111111111111111111111100100000 7
b1111111111111111111111111111100100000 ?
b101 =
1$
#400000
0$
#405000
b10000011 <
b10000011 F
b1111111 9
b1111111 A
b111111 "
b111111 /
b11111111111111111111111001000000 !
b11111111111111111111111001000000 -
b111111111111111111111111111110010000000 6
b111111 .
b111111 8
b11111111111111111111111001000000 ,
b11111111111111111111111001000000 7
b110 =
b11111111111111111111111111111001000000 ?
1$
#410000
0$
#415000
b100000011 <
b100000011 F
b11111111 9
b11111111 A
b1111111 "
b1111111 /
b11111111111111111111110010000000 !
b11111111111111111111110010000000 -
b1111111111111111111111111111100100000000 6
b1111111 .
b1111111 8
b11111111111111111111110010000000 ,
b11111111111111111111110010000000 7
b111111111111111111111111111110010000000 ?
b111 =
1$
#420000
0$
#425000
b1000000011 <
b1000000011 F
b111111111 9
b111111111 A
b11111111 "
b11111111 /
b11111111111111111111100100000000 !
b11111111111111111111100100000000 -
b11111111111111111111111111111001000000000 6
b11111111 .
b11111111 8
b11111111111111111111100100000000 ,
b11111111111111111111100100000000 7
b1000 =
b1111111111111111111111111111100100000000 ?
1$
#430000
0$
#435000
b10000000011 <
b10000000011 F
b1111111111 9
b1111111111 A
b111111111 "
b111111111 /
b11111111111111111111001000000000 !
b11111111111111111111001000000000 -
b111111111111111111111111111110010000000000 6
b111111111 .
b111111111 8
b11111111111111111111001000000000 ,
b11111111111111111111001000000000 7
b11111111111111111111111111111001000000000 ?
b1001 =
1$
#440000
0$
#445000
b100000000011 <
b100000000011 F
b11111111111 9
b11111111111 A
b1111111111 "
b1111111111 /
b11111111111111111110010000000000 !
b11111111111111111110010000000000 -
b1111111111111111111111111111100100000000000 6
b1111111111 .
b1111111111 8
b11111111111111111110010000000000 ,
b11111111111111111110010000000000 7
b1010 =
b111111111111111111111111111110010000000000 ?
1$
#450000
0$
#455000
b1000000000011 <
b1000000000011 F
b111111111111 9
b111111111111 A
b11111111111 "
b11111111111 /
b11111111111111111100100000000000 !
b11111111111111111100100000000000 -
b11111111111111111111111111111001000000000000 6
b11111111111 .
b11111111111 8
b11111111111111111100100000000000 ,
b11111111111111111100100000000000 7
b1111111111111111111111111111100100000000000 ?
b1011 =
1$
#460000
0$
#465000
b10000000000011 <
b10000000000011 F
b1111111111111 9
b1111111111111 A
b111111111111 "
b111111111111 /
b11111111111111111001000000000000 !
b11111111111111111001000000000000 -
b111111111111111111111111111110010000000000000 6
b111111111111 .
b111111111111 8
b11111111111111111001000000000000 ,
b11111111111111111001000000000000 7
b1100 =
b11111111111111111111111111111001000000000000 ?
1$
#470000
0$
#475000
b100000000000011 <
b100000000000011 F
b11111111111111 9
b11111111111111 A
b1111111111111 "
b1111111111111 /
b11111111111111110010000000000000 !
b11111111111111110010000000000000 -
b1111111111111111111111111111100100000000000000 6
b1111111111111 .
b1111111111111 8
b11111111111111110010000000000000 ,
b11111111111111110010000000000000 7
b111111111111111111111111111110010000000000000 ?
b1101 =
1$
#480000
0$
#485000
b1000000000000011 <
b1000000000000011 F
b111111111111111 9
b111111111111111 A
b11111111111111 "
b11111111111111 /
b11111111111111100100000000000000 !
b11111111111111100100000000000000 -
b11111111111111111111111111111001000000000000000 6
b11111111111111 .
b11111111111111 8
b11111111111111100100000000000000 ,
b11111111111111100100000000000000 7
b1110 =
b1111111111111111111111111111100100000000000000 ?
1$
#490000
0$
#495000
b10000000000000011 <
b10000000000000011 F
b1111111111111111 9
b1111111111111111 A
b111111111111111 "
b111111111111111 /
b11111111111111001000000000000000 !
b11111111111111001000000000000000 -
b111111111111111111111111111110010000000000000000 6
b111111111111111 .
b111111111111111 8
b11111111111111001000000000000000 ,
b11111111111111001000000000000000 7
b11111111111111111111111111111001000000000000000 ?
b1111 =
1$
#500000
0$
#505000
b100000000000000011 <
b100000000000000011 F
b11111111111111111 9
b11111111111111111 A
b1111111111111111 "
b1111111111111111 /
b11111111111110010000000000000000 !
b11111111111110010000000000000000 -
b1111111111111111111111111111100100000000000000000 6
b1111111111111111 .
b1111111111111111 8
b11111111111110010000000000000000 ,
b11111111111110010000000000000000 7
b10000 =
b111111111111111111111111111110010000000000000000 ?
1$
#510000
0$
#515000
b1000000000000000011 <
b1000000000000000011 F
b111111111111111111 9
b111111111111111111 A
b11111111111111111 "
b11111111111111111 /
b11111111111100100000000000000000 !
b11111111111100100000000000000000 -
b11111111111111111111111111111001000000000000000000 6
b11111111111111111 .
b11111111111111111 8
b11111111111100100000000000000000 ,
b11111111111100100000000000000000 7
b1111111111111111111111111111100100000000000000000 ?
b10001 =
1$
#520000
0$
#525000
b10000000000000000011 <
b10000000000000000011 F
b1111111111111111111 9
b1111111111111111111 A
b111111111111111111 "
b111111111111111111 /
b11111111111001000000000000000000 !
b11111111111001000000000000000000 -
b111111111111111111111111111110010000000000000000000 6
b111111111111111111 .
b111111111111111111 8
b11111111111001000000000000000000 ,
b11111111111001000000000000000000 7
b10010 =
b11111111111111111111111111111001000000000000000000 ?
1$
#530000
0$
#535000
b100000000000000000011 <
b100000000000000000011 F
b11111111111111111111 9
b11111111111111111111 A
b1111111111111111111 "
b1111111111111111111 /
b11111111110010000000000000000000 !
b11111111110010000000000000000000 -
b1111111111111111111111111111100100000000000000000000 6
b1111111111111111111 .
b1111111111111111111 8
b11111111110010000000000000000000 ,
b11111111110010000000000000000000 7
b111111111111111111111111111110010000000000000000000 ?
b10011 =
1$
#540000
0$
#545000
b1000000000000000000011 <
b1000000000000000000011 F
b111111111111111111111 9
b111111111111111111111 A
b11111111111111111111 "
b11111111111111111111 /
b11111111100100000000000000000000 !
b11111111100100000000000000000000 -
b11111111111111111111111111111001000000000000000000000 6
b11111111111111111111 .
b11111111111111111111 8
b11111111100100000000000000000000 ,
b11111111100100000000000000000000 7
b10100 =
b1111111111111111111111111111100100000000000000000000 ?
1$
#550000
0$
#555000
b10000000000000000000011 <
b10000000000000000000011 F
b1111111111111111111111 9
b1111111111111111111111 A
b111111111111111111111 "
b111111111111111111111 /
b11111111001000000000000000000000 !
b11111111001000000000000000000000 -
b111111111111111111111111111110010000000000000000000000 6
b111111111111111111111 .
b111111111111111111111 8
b11111111001000000000000000000000 ,
b11111111001000000000000000000000 7
b11111111111111111111111111111001000000000000000000000 ?
b10101 =
1$
#560000
0$
#565000
b100000000000000000000011 <
b100000000000000000000011 F
b11111111111111111111111 9
b11111111111111111111111 A
b1111111111111111111111 "
b1111111111111111111111 /
b11111110010000000000000000000000 !
b11111110010000000000000000000000 -
b1111111111111111111111111111100100000000000000000000000 6
b1111111111111111111111 .
b1111111111111111111111 8
b11111110010000000000000000000000 ,
b11111110010000000000000000000000 7
b10110 =
b111111111111111111111111111110010000000000000000000000 ?
1$
#570000
0$
#575000
b1000000000000000000000011 <
b1000000000000000000000011 F
b111111111111111111111111 9
b111111111111111111111111 A
b11111111111111111111111 "
b11111111111111111111111 /
b11111100100000000000000000000000 !
b11111100100000000000000000000000 -
b11111111111111111111111111111001000000000000000000000000 6
b11111111111111111111111 .
b11111111111111111111111 8
b11111100100000000000000000000000 ,
b11111100100000000000000000000000 7
b1111111111111111111111111111100100000000000000000000000 ?
b10111 =
1$
#580000
0$
#585000
b10000000000000000000000011 <
b10000000000000000000000011 F
b1111111111111111111111111 9
b1111111111111111111111111 A
b111111111111111111111111 "
b111111111111111111111111 /
b11111001000000000000000000000000 !
b11111001000000000000000000000000 -
b111111111111111111111111111110010000000000000000000000000 6
b111111111111111111111111 .
b111111111111111111111111 8
b11111001000000000000000000000000 ,
b11111001000000000000000000000000 7
b11000 =
b11111111111111111111111111111001000000000000000000000000 ?
1$
#590000
0$
#595000
b100000000000000000000000011 <
b100000000000000000000000011 F
b11111111111111111111111111 9
b11111111111111111111111111 A
b1111111111111111111111111 "
b1111111111111111111111111 /
b11110010000000000000000000000000 !
b11110010000000000000000000000000 -
b1111111111111111111111111111100100000000000000000000000000 6
b1111111111111111111111111 .
b1111111111111111111111111 8
b11110010000000000000000000000000 ,
b11110010000000000000000000000000 7
b111111111111111111111111111110010000000000000000000000000 ?
b11001 =
1$
#600000
0$
