signle_clk_cpu/defines.v

// common define
`define datawidth                           32
`define RstEnable                           1'b0
`define RstDisable                          1'b1
`define ZeroWord                            32'd0
`define ZeroReg                             5'd0
//instr_RAM
`define addrwidth                           8
//ALU
`define ALU_CLT                             3:0
`define SHIFT_NUM_width                     4:0
`define shift_ctr                           1:0
//diver
`define DIV_STEPS                           32
`define DIV_STEPS_Log2                      6
//*************
`define CpuResetAddr                        32'h0


`define WriteEnable                         1'b1
`define WriteDisable                        1'b0
`define ReadEnable                          1'b1
`define ReadDisable                         1'b0
`define True                                1'b1
`define False                               1'b0
`define ChipEnable                          1'b1
`define ChipDisable                         1'b0
`define JumpEnable                          1'b1
`define JumpDisable                         1'b0
`define DivResultNotReady                   1'b0
`define DivResultReady                      1'b1
`define DivStart                            1'b1
`define DivStop                             1'b0
`define HoldEnable                          1'b1
`define HoldDisable                         1'b0
`define Stop                                1'b1
`define NoStop                              1'b0
`define RIB_ACK                             1'b1
`define RIB_NACK                            1'b0
`define RIB_REQ                             1'b1
`define RIB_NREQ                            1'b0
`define INT_ASSERT                          1'b1
`define INT_DEASSERT                        1'b0

`define INT_BUS                             7:0
`define INT_NONE                            8'h0
`define INT_RET                             8'hff
`define INT_TIMER0                          8'b00000001
`define INT_TIMER0_ENTRY_ADDR               32'h4

`define Hold_Flag_Bus                       2:0
`define Hold_None                           3'b000
`define Hold_Pc                             3'b001
`define Hold_If                             3'b010
`define Hold_Id                             3'b011

// I type inst
`define I_TYPE                              7'b0010011
`define INST_ADDI                           3'b000
`define INST_SLTI                           3'b010
`define INST_SLTIU                          3'b011
`define INST_XORI                           3'b100
`define INST_ORI                            3'b110
`define INST_ANDI                           3'b111
`define INST_SLLI                           3'b001
`define INST_SRI                            3'b101



// L type inst
`define L_TYPE                              7'b0000011
`define INST_LB                             3'b000
`define INST_LH                             3'b001
`define INST_LW                             3'b010
`define INST_LBU                            3'b100
`define INST_LHU                            3'b101
`define lb  			                    3'b000
`define lh  			                    3'b010
`define lw		                            3'b011
`define lbu  			                    3'b100
`define lhu  			                    3'b110


// S type inst
`define S_TYPE                              7'b0100011
`define sb  			                    3'b000
`define sh  			                    3'b001
`define sw  			                    3'b010

// R and M type inst
`define R_TYPE                              7'b0110011
// R type inst
`define INST_ADD_SUB                        3'b000
`define INST_SLL                            3'b001
`define INST_SLT                            3'b010
`define INST_SLTU                           3'b011
`define INST_XOR                            3'b100
`define INST_SR                             3'b101
`define INST_OR                             3'b110
`define INST_AND                            3'b111
// M type inst
`define INST_MUL                            3'b000
`define INST_MULH                           3'b001
`define INST_MULHSU                         3'b010
`define INST_MULHU                          3'b011
`define INST_DIV                            3'b100
`define INST_DIVU                           3'b101
`define INST_REM                            3'b110
`define INST_REMU                           3'b111

// J type inst
`define INST_JAL                            7'b1101111
`define INST_JALR                           7'b1100111
//U type inst
`define INST_LUI                            7'b0110111
`define INST_AUIPC                          7'b0010111


`define INST_NOP                            32'h00000001
`define INST_NOP_OP                         7'b0000001
`define INST_MRET                           32'h30200073
`define INST_RET                            32'h0000
`define INST_FENCE                          7'b0001111
`define INST_ECALL                          32'h73
`define INST_EBREAK                         32'h00100073

// B type inst
`define B_TYPE                              7'b1100011
`define INST_BEQ                            3'b000
`define INST_BNE                            3'b001
`define INST_BLT                            3'b100
`define INST_BGE                            3'b101
`define INST_BLTU                           3'b110
`define INST_BGEU                           3'b111

// CSR inst
`define CSR_TYPE                            7'b1110011
`define INST_CSRRW                          3'b001
`define INST_CSRRS                          3'b010
`define INST_CSRRC                          3'b011
`define INST_CSRRWI                         3'b101
`define INST_CSRRSI                         3'b110
`define INST_CSRRCI                         3'b111
// FENCE inst
`define FENCE_TYPE                          7'b0001111        
// CSR reg addr
`define CSR_CYCLE                           12'hc00
`define CSR_CYCLEH                          12'hc80
`define CSR_MTVEC                           12'h305
`define CSR_MCAUSE                          12'h342
`define CSR_MEPC                            12'h341
`define CSR_MIE                             12'h304
`define CSR_MSTATUS                         12'h300
`define CSR_MSCRATCH                        12'h340

`define RomNum                              4096  // rom depth(how many words)

`define MemNum                              4096  // memory depth(how many words)
`define MemBus                              31:0
`define MemAddrBus                          31:0

`define InstBus                             31:0
`define InstAddrBus                         31:0

// common regs
`define RegAddrBus                          4:0
`define RegBus                              31:0
`define DoubleRegBus                        63:0
`define RegWidth                            32
`define RegNum                              32        // reg num
`define RegNumLog2                          5


//saturating_counter
`define strong_not_taken                    2'b00
`define weakly_not_taken                    2'b01
`define weakly_taken                        2'b10
`define strong_taken                        2'b11

pipeline_cpu/saturating_counter_2bits.v
`include "defines.v"
module saturating_counter_2bits (
    input clk,
    input rst_n,
    input taken_flag,
    output reg predicted_taken
);
reg [1:0] cnt;
wire add_flag,sub_flag;

always @(posedge clk ) begin

       if (! rst_n)begin
           cnt<= `strong_not_taken;
           end
       else if ( add_flag && cnt != `strong_taken)
            begin
                 cnt<=cnt+1;
            end
       else if ( sub_flag && cnt != `strong_not_taken)
            begin
                 cnt<=cnt-1;
            end
        else begin
            
            cnt<=cnt ;
        end
end

always @(*) begin
    case(cnt) 
    `strong_not_taken:begin
        predicted_taken = 0;
    end
    `weakly_not_taken:begin
        predicted_taken = 0;
    end
    `weakly_taken:begin
        predicted_taken = 1;
    end
    `strong_taken:begin
        predicted_taken = 1;
    end  
    default : predicted_taken = 0;                
    endcase
end

assign add_flag = taken_flag;
assign sub_flag = ~taken_flag;

endmodule //saturating_counter_2bits

pipeline_cpu/tb_saturating_counter_2bits.v
`timescale  1ns / 1ps
`include "saturating_counter_2bits.v"
module tb_saturating_counter_2bits;   

// saturating_counter_2bits Parameters
parameter PERIOD  = 10;


// saturating_counter_2bits Inputs
reg   clk                                  = 0 ;
reg   rst_n                                = 0 ;
reg   taken_flag                           = 0 ;

// saturating_counter_2bits Outputs
wire  predicted_taken                      ;


initial
begin
    forever #(PERIOD/2)  clk=~clk;
end

initial
begin
    #(PERIOD*2) rst_n  =  1;
end

saturating_counter_2bits  u_saturating_counter_2bits (
    .clk                     ( clk               ),
    .rst_n                   ( rst_n             ),
    .taken_flag              ( taken_flag        ),

    .predicted_taken         ( predicted_taken   )
);

initial
begin
    $dumpfile("saturating_counter_2bits_.vcd");
    $dumpvars    ;
    # (1*PERIOD)
    taken_flag = 1;
    # (6*PERIOD)
    taken_flag = 0;
    # (5*PERIOD)
    taken_flag = 1;
    # (4*PERIOD)
    taken_flag = 0;
    # (2*PERIOD)
    taken_flag = 1;
    # (1*PERIOD)
    taken_flag = 0;
    # (1*PERIOD)
    $finish;
end

endmodule

pipeline_cpu/saturating_counter_2bits_.vcd
$date
	Mon May 23 20:08:34 2022
$end
$version
	Icarus Verilog
$end
$timescale
	1ps
$end
$scope module tb_saturating_counter_2bits $end
$var wire 1 ! predicted_taken $end
$var reg 1 " clk $end
$var reg 1 # rst_n $end
$var reg 1 $ taken_flag $end
$scope module u_saturating_counter_2bits $end
$var wire 1 % add_flag $end
$var wire 1 " clk $end
$var wire 1 # rst_n $end
$var wire 1 & sub_flag $end
$var wire 1 $ taken_flag $end
$var reg 2 ' cnt [1:0] $end
$var reg 1 ! predicted_taken $end
$upscope $end
$upscope $end
$enddefinitions $end
#0
$dumpvars
bx '
1&
0%
0$
0#
0"
x!
$end
#5000
0!
b0 '
1"
#10000
0&
0"
1%
1$
#15000
1"
#20000
0"
1#
#25000
b1 '
1"
#30000
0"
#35000
1!
b10 '
1"
#40000
0"
#45000
b11 '
1"
#50000
0"
#55000
1"
#60000
0"
#65000
1"
#70000
1&
0"
0%
0$
#75000
b10 '
1"
#80000
0"
#85000
0!
b1 '
1"
#90000
0"
#95000
b0 '
1"
#100000
0"
#105000
1"
#110000
0"
#115000
1"
#120000
0&
0"
1%
1$
#125000
b1 '
1"
#130000
0"
#135000
1!
b10 '
1"
#140000
0"
#145000
b11 '
1"
#150000
0"
#155000
1"
#160000
1&
0"
0%
0$
#165000
b10 '
1"
#170000
0"
#175000
0!
b1 '
1"
#180000
0&
0"
1%
1$
#185000
1!
b10 '
1"
#190000
1&
0"
0%
0$
#195000
0!
b1 '
1"
