pipeline_cpu/stallable_pipeline.v
module stallable_pipeline #(parameter WIDTH = 32)(
    input clk,
    input rst_n,
    input validin,
    input [WIDTH-1:0] datain,
    input out_allow,
    input pipe1_ready_go,
    output validout,
    output [WIDTH-1:0] dataout
);
reg pipe1_valid;
reg pipe2_valid;
reg pipe3_valid;
reg [WIDTH-1:0] pipe1_data;
reg [WIDTH-1:0] pipe2_data;
reg [WIDTH-1:0] pipe3_data;

wire pipe1_allowin;
wire pipe1_ready_go;
wire pipe1_to_pipe2_vaild;

wire pipe2_allowin;
wire pipe2_ready_go;
wire pipe2_to_pipe3_vaild;

wire pipe3_allowin;
wire pipe3_ready_go;

//assign pipe1_ready_go=1;
assign pipe1_allowin = !pipe1_valid || (pipe1_ready_go && pipe2_allowin);//当前级允许数据输入的情况：1：上级数据未准备好；2：本级数据处理完成且下级发起读数据请求
assign pipe1_to_pipe2_vaild = pipe1_valid && pipe1_ready_go;//上级有数据要输入且本级数据处理完成，向下一级发起数据传输请求。

always @(posedge clk ) begin

    if(!rst_n)
        pipe1_valid <= 1'b0;
    else if (pipe1_allowin)
        pipe1_valid <= validin;
    if (validin && pipe1_allowin)//validin由0变1时，pipe1完成对上级数据的接收，并且在数据处理完成后向下一级发起发送数据请求。
        pipe1_data <= datain;
end

assign pipe2_ready_go=1;
assign pipe2_allowin = !pipe2_valid || pipe2_ready_go && pipe3_allowin;
assign pipe2_to_pipe3_vaild = pipe2_valid && pipe2_ready_go;

always @(posedge clk ) begin

    if(!rst_n)
        pipe2_valid <= 1'b0;
    else if (pipe2_allowin)
        pipe2_valid <= pipe1_to_pipe2_vaild;
    if (pipe1_to_pipe2_vaild && pipe2_allowin)
        pipe2_data <= pipe1_data;
end

assign pipe3_ready_go=1;
assign pipe3_allowin = !pipe3_valid || pipe3_ready_go && out_allow;
assign validout = pipe3_valid && pipe3_ready_go;
 
always @(posedge clk ) begin

    if(!rst_n)
        pipe3_valid <= 1'b0;
    else if (pipe3_allowin)
        pipe3_valid <= pipe2_to_pipe3_vaild;
    if (pipe2_to_pipe3_vaild && pipe3_allowin)
        pipe3_data <= pipe2_data;
end

assign dataout = pipe3_data ;
endmodule //stallable_pipeline

pipeline_cpu/tb_stallable_pipeline.v
`timescale  1ns / 1ps        
`include "stallable_pipeline.v"
module tb_stallable_pipeline;

// stallable_pipeline Parameters
parameter PERIOD  = 10;


// stallable_pipeline Inputs
reg   clk                                  = 0 ;
reg   rst_n                                = 0 ;
reg   validin                              = 0 ;
reg   [31:0]  datain                  = 0 ;
reg   out_allow                            = 0 ;
reg   pipe1_ready_go                       = 0 ;

// stallable_pipeline Outputs
wire  validout                             ;
wire  [31:0]  dataout                 ;


initial
begin
    forever #(PERIOD/2)  clk=~clk;
end

initial
begin
    #(PERIOD*2) rst_n  =  1;
end

stallable_pipeline  u_stallable_pipeline (
    .clk                     ( clk                         ),
    .rst_n                   ( rst_n                       ),
    .validin                 ( validin                     ),
    .datain                  ( datain           ),
    .out_allow               ( out_allow                   ),
    .pipe1_ready_go          ( pipe1_ready_go              ),

    .validout                ( validout                    ),
    .dataout                 ( dataout          )
);

initial
begin
    $dumpfile("stallable_pipeline.vcd");
    $dumpvars    ;
    #20
    datain=32'd4;
    validin=1;
    pipe1_ready_go = 1;
    out_allow=1;
    #20
    datain=32'd18;
    validin=1;
    pipe1_ready_go = 0;
    out_allow=1;
    #10
    datain=32'd24;
    validin=1;
    pipe1_ready_go = 1;
    out_allow=1;
    #10
    datain=32'd28;
    validin=1;
    pipe1_ready_go = 1;
    out_allow=0;
    #10
    datain=32'd32;
    validin=1;
    pipe1_ready_go = 1;
    out_allow=1;
    #10

    $finish;
end

endmodule

pipeline_cpu/stallable_pipeline.vcd
$date
	Sun Jul 10 20:51:02 2022
$end
$version
	Icarus Verilog
$end
$timescale
	1ps
$end
$scope module tb_stallable_pipeline $end
$var wire 1 ! validout $end
$var wire 32 " dataout [31:0] $end
$var reg 1 # clk $end
$var reg 32 $ datain [31:0] $end
$var reg 1 % out_allow $end
$var reg 1 & pipe1_ready_go $end
$var reg 1 ' rst_n $end
$var reg 1 ( validin $end
$scope module u_stallable_pipeline $end
$var wire 1 # clk $end
$var wire 32 ) datain [31:0] $end
$var wire 32 * dataout [31:0] $end
$var wire 1 % out_allow $end
$var wire 1 + pipe1_allowin $end
$var wire 1 & pipe1_ready_go $end
$var wire 1 , pipe1_to_pipe2_vaild $end
$var wire 1 - pipe2_allowin $end
$var wire 1 . pipe2_ready_go $end
$var wire 1 / pipe2_to_pipe3_vaild $end
$var wire 1 0 pipe3_allowin $end
$var wire 1 1 pipe3_ready_go $end
$var wire 1 ' rst_n $end
$var wire 1 ( validin $end
$var wire 1 ! validout $end
$var reg 32 2 pipe1_data [31:0] $end
$var reg 1 3 pipe1_valid $end
$var reg 32 4 pipe2_data [31:0] $end
$var reg 1 5 pipe2_valid $end
$var reg 32 6 pipe3_data [31:0] $end
$var reg 1 7 pipe3_valid $end
$upscope $end
$upscope $end
$enddefinitions $end
#0
$dumpvars
x7
bx 6
x5
bx 4
x3
bx 2
11
x0
x/
1.
x-
0,
x+
bx *
b0 )
0(
0'
0&
0%
b0 $
0#
bx "
x!
$end
#5000
1+
1-
0/
10
0!
03
05
07
1#
#10000
0#
#15000
1#
#20000
0#
1%
1&
1(
b100 $
b100 )
1'
#25000
1,
b100 2
13
1#
#30000
0#
#35000
1/
b100 4
15
1#
#40000
0+
0,
0#
0&
b10010 $
b10010 )
#45000
0/
1!
05
b100 "
b100 *
b100 6
17
1#
#50000
1+
1,
0#
1&
b11000 $
b11000 )
#55000
0!
1/
07
15
b11000 2
1#
#60000
0#
0%
b11100 $
b11100 )
#65000
0+
0-
00
1!
b11100 2
b11000 4
17
1#
#70000
1+
1-
10
0#
1%
b100000 $
b100000 )
#75000
b11000 "
b11000 *
b11000 6
b11100 4
b100000 2
1#
