iverilog_uart/counter.v
module counter
#(parameter cnt_max=32)(
    clk,
    rst_n,
    cnt_add,
    cnt,
    cnt_end
);

/////////////////////////////////////////////////////////////////////////////////////
function integer clogb2 (
    input           integer depth
    );
begin
    if(depth == 0)
        clogb2  = 1;
    else if(depth != 0)
        for(clogb2  = 0; depth > 0;clogb2  = clogb2  + 1)
            depth = depth >> 1;
end
endfunction
localparam cnt_width = clogb2 (cnt_max);
////////////////////////////////////////////////////////////////////////////////////
    input clk     ;
    input rst_n   ;
    input cnt_add ;
    output reg [cnt_width-1:0] cnt ;
    output cnt_end;

always @(posedge clk or negedge rst_n) begin
    if (rst_n == 1'b0)
        cnt<=0;
    else if (cnt_add) 
                begin
                    if (cnt_end)
                        cnt<=0;
                    else
                        cnt<=cnt+1;
                end
end
assign cnt_end = cnt_add && cnt ==  cnt_max -1;
endmodule //counter

iverilog_uart/tb_counter.v
`timescale  1ns / 1ps
`include "counter.v"
module tb_counter;   

// counter Parameters
parameter PERIOD   = 10;
parameter cnt_max  = 32;

// counter Inputs
reg   clk                                  = 0 ;
reg   rst_n                                = 0 ;
reg   cnt_add                              = 0 ;

// counter Outputs
wire  cnt_end                              ;


initial
begin
    forever #(PERIOD/2)  clk=~clk;
end

initial
begin
    #(PERIOD*2) rst_n  =  1;
end

counter #(
    .cnt_max ( cnt_max ))
 u_counter (
    .clk                     ( clk       ),
    .rst_n                   ( rst_n     ),
    .cnt_add                 ( cnt_add   ),

    .cnt_end                 ( cnt_end   )
);

initial
begin
    $dumpfile("counter.vcd");
    $dumpvars    ;
    #20
    cnt_add = 1;
    #320
    $finish;
end

endmodule

iverilog_uart/counter.vcd
$date
	Thu Jul 28 20:06:17 2022
$end
$version
	Icarus Verilog
$end
$timescale
	1ps
$end
$scope module tb_counter $end
$var wire 1 ! cnt_end $end
$var reg 1 " clk $end
$var reg 1 # cnt_add $end
$var reg 1 $ rst_n $end
$scope module u_counter $end
$var wire 1 " clk $end
$var wire 1 # cnt_add $end
$var wire 1 $ rst_n $end
$var wire 1 ! cnt_end $end
$var reg 5 % cnt [4:0] $end
$upscope $end
$upscope $end
$enddefinitions $end
#0
$dumpvars
b0 %
0$
0#
0"
0!
$end
#5000
1"
#10000
0"
#15000
1"
#20000
0"
1#
1$
#25000
b1 %
1"
#30000
0"
#35000
b10 %
1"
#40000
0"
#45000
b11 %
1"
#50000
0"
#55000
b100 %
1"
#60000
0"
#65000
b101 %
1"
#70000
0"
#75000
1!
b110 %
1"
#80000
0"
#85000
0!
b0 %
1"
#90000
0"
#95000
b1 %
1"
#100000
0"
#105000
b10 %
1"
#110000
0"
#115000
b11 %
1"
#120000
0"
#125000
b100 %
1"
#130000
0"
#135000
b101 %
1"
#140000
0"
#145000
1!
b110 %
1"
#150000
0"
#155000
0!
b0 %
1"
#160000
0"
#165000
b1 %
1"
#170000
0"
#175000
b10 %
1"
#180000
0"
#185000
b11 %
1"
#190000
0"
#195000
b100 %
1"
#200000
0"
#205000
b101 %
1"
#210000
0"
#215000
1!
b110 %
1"
#220000
0"
#225000
0!
b0 %
1"
#230000
0"
#235000
b1 %
1"
#240000
0"
#245000
b10 %
1"
#250000
0"
#255000
b11 %
1"
#260000
0"
#265000
b100 %
1"
#270000
0"
#275000
b101 %
1"
#280000
0"
#285000
1!
b110 %
1"
#290000
0"
#295000
0!
b0 %
1"
#300000
0"
#305000
b1 %
1"
#310000
0"
#315000
b10 %
1"
#320000
0"
#325000
b11 %
1"
#330000
0"
#335000
b100 %
1"
