iverilog_uart/counter.v
module counter
#(parameter cnt_max=32)(
    clk,
    rst_n,
    cnt_add,
    cnt,
    cnt_end
);

/////////////////////////////////////////////////////////////////////////////////////
function integer clogb2 (
    input           integer depth
    );
begin
    if(depth == 0)
        clogb2  = 1;
    else if(depth != 0)
        for(clogb2  = 0; depth > 0;clogb2  = clogb2  + 1)
            depth = depth >> 1;
end
endfunction
localparam cnt_width = clogb2 (cnt_max);
////////////////////////////////////////////////////////////////////////////////////
    input clk     ;
    input rst_n   ;
    input cnt_add ;
    output reg [cnt_width-1:0] cnt ;
    output cnt_end;

always @(posedge clk or negedge rst_n) begin
    if (rst_n == 1'b0)
        cnt<=0;
    else if (cnt_add) 
                begin
                    if (cnt_end)
                        cnt<=0;
                    else
                        cnt<=cnt+1;
                end
end
assign cnt_end = cnt_add && cnt ==  cnt_max -1;
endmodule //counter

iverilog_uart/uart_rx.v
`include "counter.v"
module uart_rx #(parameter datawidth = 8 , Baudrate = 9600  )(
   input clk,
   input rst_n,
   input rxd,
   output [datawidth-1:0] data_out,
   output reg rx_valid
);
//////////////////////////////////////////////////////////////////////////////////////////////////////////////////////////
localparam  cnt_max1 = 50000000/Baudrate;
localparam  cnt_max2 = datawidth +1;
function integer clogb2 (
    input           integer depth
    );
begin
    if(depth == 0)
        clogb2  = 1;
    else if(depth != 0)
        for(clogb2  = 0; depth > 0;clogb2  = clogb2  + 1)
            depth = depth >> 1;
end
endfunction
localparam cnt_width1 = clogb2 (cnt_max1);
localparam cnt_width2 = clogb2 (cnt_max2);

//////////////////////////////////////////////////////////////////////////////////////////////////////////////////////////
reg bitlenth_counter_add_reg1;
reg bitlenth_counter_add_reg2;
reg bitlenth_counter_add_reg3;
always @(posedge clk or negedge rst_n) begin
   if (!rst_n)
   begin
      bitlenth_counter_add_reg1<=1; 
      bitlenth_counter_add_reg2<=1;
      bitlenth_counter_add_reg3<=1;
   end
   else
      begin
         //异步信号同步化
         bitlenth_counter_add_reg1<=rxd;
         bitlenth_counter_add_reg2<=bitlenth_counter_add_reg1;
         //边沿检测
         bitlenth_counter_add_reg3<=bitlenth_counter_add_reg2;         
      end
end
wire rx_neg_edge,rx_pos_edge;
assign rx_neg_edge = ~bitlenth_counter_add_reg2 & bitlenth_counter_add_reg3 ;
//assign rx_pos_edge = bitlenth_counter_add_reg2 == 1 && bitlenth_counter_add_reg3 == 1;

reg add_flag;
wire cnt_end1,cnt_end2;
wire [cnt_width1-1:0] cnt1;
wire [cnt_width2-1:0] cnt2;

counter #(
    .cnt_max ( cnt_max1 ))
 bitlenth_counter(
    .clk         ( clk         ),
    .rst_n       ( rst_n       ),
    .cnt_add     ( add_flag    ),
    .cnt         ( cnt1        ),
    .cnt_end     ( cnt_end1    )
);

counter #(
    .cnt_max ( cnt_max2 ))
 bitnum_counter(
    .clk         ( clk         ),
    .rst_n       ( rst_n       ),
    .cnt_add     ( cnt_end1    ),
    .cnt         ( cnt2        ),
    .cnt_end     ( cnt_end2    )
);
always @(posedge clk or negedge rst_n) begin
   if(!rst_n)begin
      add_flag <= 0;
      rx_valid<=0;
   end
   else if (rx_neg_edge) begin
      add_flag<=1 ;
      rx_valid<=0;
   end
   else if (cnt_end2) begin
      add_flag <=0;
      rx_valid<=1;
   end

end
reg [datawidth-1:0] rx_data;
always @(posedge clk or negedge rst_n) begin
   if (!rst_n)begin
      rx_data<=0;
   end
   else if (add_flag && cnt1 == cnt_max1 /2 && cnt2 > 0 )begin
      rx_data <= {bitlenth_counter_add_reg2,rx_data[datawidth-1:1]};
   end
end
assign data_out = rx_data;
endmodule //uart_rx

iverilog_uart/tb_uart_rx.v
`timescale  1ns / 1ps
`include "uart_rx.v"
module tb_uart_rx;   

// uart_rx Parameters
parameter PERIOD  = 10;


// uart_rx Inputs
reg   clk                                  = 0 ;
reg   rxd                                  = 1 ;
reg   rst_n                                = 0 ;

// uart_rx Outputs
wire  rx_valid                              ;
wire  [7:0]  data_out                       ;

initial
begin
    forever #(PERIOD/2)  clk=~clk;
end

initial
begin
    #(PERIOD*2) rst_n  =  1;
end

uart_rx#(
    .datawidth ( 8 ),
    .Baudrate   ( 9600 )
)u_uart_rx(
    .clk       ( clk       ),
    .rst_n     ( rst_n     ),
    .rxd       ( rxd       ),
    .data_out  ( data_out  ),
    .rx_valid  ( rx_valid  )
);


initial
begin
    $dumpfile("uart_rx.vcd");
    $dumpvars    ;
    #20
    rxd = 0;
    #50
    rxd= 1 ;
    #50
    rxd= 1 ;
    #50
    rxd= 1 ;
    #50
    rxd= 1 ;
    #50
    rxd= 0 ;
    #50
    rxd= 0 ;
    #50
    rxd= 0 ;
    #50
    rxd= 0 ;
    #50
    rxd= 1 ;
    #100
    $finish;
end

endmodule

iverilog_uart/uart_rx.vcd
$date
	Fri Jul 29 10:00:39 2022
$end
$version
	Icarus Verilog
$end
$timescale
	1ps
$end
$scope module tb_uart_rx $end
$var wire 1 ! rx_valid $end
$var wire 8 " data_out [7:0] $end
$var reg 1 # clk $end
$var reg 1 $ rst_n $end
$var reg 1 % rxd $end
$scope module u_uart_rx $end
$var wire 1 # clk $end
$var wire 8 & data_out [7:0] $end
$var wire 1 $ rst_n $end
$var wire 1 ' rx_neg_edge $end
$var wire 1 % rxd $end
$var wire 1 ( cnt_end2 $end
$var wire 1 ) cnt_end1 $end
$var wire 4 * cnt2 [3:0] $end
$var wire 3 + cnt1 [2:0] $end
$var reg 1 , add_flag $end
$var reg 1 - bitlenth_counter_add_reg1 $end
$var reg 1 . bitlenth_counter_add_reg2 $end
$var reg 1 / bitlenth_counter_add_reg3 $end
$var reg 8 0 rx_data [7:0] $end
$var reg 1 ! rx_valid $end
$scope function clogb2 $end
$var integer 32 1 depth [31:0] $end
$upscope $end
$scope module bitlenth_counter $end
$var wire 1 # clk $end
$var wire 1 , cnt_add $end
$var wire 1 ) cnt_end $end
$var wire 1 $ rst_n $end
$var reg 3 2 cnt [2:0] $end
$scope function clogb2 $end
$var integer 32 3 depth [31:0] $end
$upscope $end
$upscope $end
$scope module bitnum_counter $end
$var wire 1 # clk $end
$var wire 1 ) cnt_add $end
$var wire 1 ( cnt_end $end
$var wire 1 $ rst_n $end
$var reg 4 4 cnt [3:0] $end
$scope function clogb2 $end
$var integer 32 5 depth [31:0] $end
$upscope $end
$upscope $end
$upscope $end
$upscope $end
$enddefinitions $end
#0
$dumpvars
bx 5
b0 4
bx 3
b0 2
bx 1
b0 0
1/
1.
1-
0,
b0 +
b0 *
0)
0(
0'
b0 &
1%
0$
0#
b0 "
0!
$end
#5000
1#
#10000
0#
#15000
1#
#20000
0#
0%
1$
#25000
0-
1#
#30000
0#
#35000
1'
0.
1#
#40000
0#
#45000
0'
1,
0/
1#
#50000
0#
#55000
b1 +
b1 2
1#
#60000
0#
#65000
b10 +
b10 2
1#
#70000
0#
1%
#75000
b11 +
b11 2
1-
1#
#80000
0#
#85000
1)
1.
b100 +
b100 2
1#
#90000
0#
#95000
0)
b0 +
b0 2
b1 *
b1 4
1/
1#
#100000
0#
#105000
b1 +
b1 2
1#
#110000
0#
#115000
b10 +
b10 2
1#
#120000
0#
#125000
b10000000 "
b10000000 &
b10000000 0
b11 +
b11 2
1#
#130000
0#
#135000
1)
b100 +
b100 2
1#
#140000
0#
#145000
0)
b10 *
b10 4
b0 +
b0 2
1#
#150000
0#
#155000
b1 +
b1 2
1#
#160000
0#
#165000
b10 +
b10 2
1#
#170000
0#
#175000
b11 +
b11 2
b11000000 "
b11000000 &
b11000000 0
1#
#180000
0#
#185000
1)
b100 +
b100 2
1#
#190000
0#
#195000
0)
b0 +
b0 2
b11 *
b11 4
1#
#200000
0#
#205000
b1 +
b1 2
1#
#210000
0#
#215000
b10 +
b10 2
1#
#220000
0#
#225000
b11100000 "
b11100000 &
b11100000 0
b11 +
b11 2
1#
#230000
0#
#235000
1)
b100 +
b100 2
1#
#240000
0#
#245000
0)
b100 *
b100 4
b0 +
b0 2
1#
#250000
0#
#255000
b1 +
b1 2
1#
#260000
0#
#265000
b10 +
b10 2
1#
#270000
0#
0%
#275000
b11 +
b11 2
0-
b11110000 "
b11110000 &
b11110000 0
1#
#280000
0#
#285000
1'
1)
0.
b100 +
b100 2
1#
#290000
0#
#295000
0)
0'
b0 +
b0 2
b101 *
b101 4
0/
1#
#300000
0#
#305000
b1 +
b1 2
1#
#310000
0#
#315000
b10 +
b10 2
1#
#320000
0#
#325000
b1111000 "
b1111000 &
b1111000 0
b11 +
b11 2
1#
#330000
0#
#335000
1)
b100 +
b100 2
1#
#340000
0#
#345000
0)
b110 *
b110 4
b0 +
b0 2
1#
#350000
0#
#355000
b1 +
b1 2
1#
#360000
0#
#365000
b10 +
b10 2
1#
#370000
0#
#375000
b11 +
b11 2
b111100 "
b111100 &
b111100 0
1#
#380000
0#
#385000
1)
b100 +
b100 2
1#
#390000
0#
#395000
0)
b0 +
b0 2
b111 *
b111 4
1#
#400000
0#
#405000
b1 +
b1 2
1#
#410000
0#
#415000
b10 +
b10 2
1#
#420000
0#
#425000
b11110 "
b11110 &
b11110 0
b11 +
b11 2
1#
#430000
0#
#435000
1)
b100 +
b100 2
1#
#440000
0#
#445000
0)
b1000 *
b1000 4
b0 +
b0 2
1#
#450000
0#
#455000
b1 +
b1 2
1#
#460000
0#
#465000
b10 +
b10 2
1#
#470000
0#
1%
#475000
b11 +
b11 2
1-
b1111 "
b1111 &
b1111 0
1#
#480000
0#
#485000
1(
1)
1.
b100 +
b100 2
1#
#490000
0#
#495000
0(
0)
b0 +
b0 2
b0 *
b0 4
1/
1!
0,
1#
