iverilog_uart/counter.v
module counter
#(parameter cnt_max=32)(
    clk,
    rst_n,
    cnt_add,
    cnt,
    cnt_end
);

/////////////////////////////////////////////////////////////////////////////////////
function integer clogb2 (
    input           integer depth
    );
begin
    if(depth == 0)
        clogb2  = 1;
    else if(depth != 0)
        for(clogb2  = 0; depth > 0;clogb2  = clogb2  + 1)
            depth = depth >> 1;
end
endfunction
localparam cnt_width = clogb2 (cnt_max);
////////////////////////////////////////////////////////////////////////////////////
    input clk     ;
    input rst_n   ;
    input cnt_add ;
    output reg [cnt_width-1:0] cnt ;
    output cnt_end;

always @(posedge clk or negedge rst_n) begin
    if (rst_n == 1'b0)
        cnt<=0;
    else if (cnt_add) 
                begin
                    if (cnt_end)
                        cnt<=0;
                    else
                        cnt<=cnt+1;
                end
end
assign cnt_end = cnt_add && cnt ==  cnt_max -1;
endmodule //counter

iverilog_uart/uart_rx.v
`include "counter.v"
module uart_rx #(parameter datawidth = 5 , Baudrate = 9600  )(
   input clk,
   input rst_n,
   input rx,
   output reg [datawidth-1:0] data
);
//////////////////////////////////////////////////////////////////////////////////////////////////////////////////////////
localparam  cnt_max1 = 50000000/Baudrate;
localparam  cnt_max2 = datawidth +1;
function integer clogb2 (
    input           integer depth
    );
begin
    if(depth == 0)
        clogb2  = 1;
    else if(depth != 0)
        for(clogb2  = 0; depth > 0;clogb2  = clogb2  + 1)
            depth = depth >> 1;
end
endfunction
localparam cnt_width1 = clogb2 (cnt_max1);
localparam cnt_width2 = clogb2 (cnt_max2);

//////////////////////////////////////////////////////////////////////////////////////////////////////////////////////////
reg bitlenth_counter_add_reg1;
reg bitlenth_counter_add_reg2;
reg bitlenth_counter_add_reg3;
always @(posedge clk or negedge rst_n) begin
   if (!rst_n)
   begin
      bitlenth_counter_add_reg1<=1; 
      bitlenth_counter_add_reg2<=1;
      bitlenth_counter_add_reg3<=1;
   end
   else
      begin
         //异步信号同步化
         bitlenth_counter_add_reg1<=rx;
         bitlenth_counter_add_reg2<=bitlenth_counter_add_reg1;
         //边沿检测
         bitlenth_counter_add_reg3<=bitlenth_counter_add_reg2;         
      end
end
wire rx_neg_edge,rx_pos_edge;
assign rx_neg_edge = bitlenth_counter_add_reg2 == 0 && bitlenth_counter_add_reg3 == 1;
//assign rx_pos_edge = bitlenth_counter_add_reg2 == 1 && bitlenth_counter_add_reg3 == 1;

reg add_flag;
wire cnt_end1,cnt_end2;
wire [cnt_width1-1:0] cnt1;
wire [cnt_width2-1:0] cnt2;
always @(posedge clk or negedge rst_n) begin
   if(!rst_n)begin
      add_flag <= 0;
   end
   else if (rx_neg_edge) begin
      add_flag<=1 ;
   end
   else if (cnt_end2) begin
      add_flag <=0;
   end

end
counter #(
    .cnt_max ( cnt_max1 ))
 bitlenth_counter(
    .clk         ( clk         ),
    .rst_n       ( rst_n       ),
    .cnt_add     ( add_flag    ),
    .cnt         ( cnt1        ),
    .cnt_end     ( cnt_end1    )
);

counter #(
    .cnt_max ( cnt_max2 ))
 bitnum_counter(
    .clk         ( clk         ),
    .rst_n       ( rst_n       ),
    .cnt_add     ( cnt_end1    ),
    .cnt         ( cnt2        ),
    .cnt_end     ( cnt_end2    )
);

always @(posedge clk or negedge rst_n) begin
   if (!rst_n)begin
      data<=0;
   end
   else if (add_flag && cnt1 == cnt_max1 /2 && cnt_end2 > 0)begin
      data [cnt_end2 - 1] <= bitlenth_counter_add_reg2; 
   end
end

endmodule //uart_rx

iverilog_uart/tb_uart_rx.v
`timescale  1ns / 1ps
`include "uart_rx.v"
module tb_uart_rx;   

// uart_rx Parameters
parameter PERIOD  = 10;


// uart_rx Inputs
reg   clk                                  = 0 ;
reg   rst_n                                = 0 ;
reg   cnt_add                              = 0 ;

// uart_rx Outputs
wire  cnt_end                              ;


initial
begin
    forever #(PERIOD/2)  clk=~clk;
end

initial
begin
    #(PERIOD*2) rst_n  =  1;
end

uart_rx#(
    .datawidth ( 5 ),
    .Baudrate  ( 9600 )
)u_uart_rx(
    .clk       ( clk       ),
    .rst_n     ( rst_n     ),
    .cnt_add   ( cnt_add   ),
    .cnt_end   ( cnt_end   )
);

initial
begin
    $dumpfile("uart_rx.vcd");
    $dumpvars    ;
    #20

    cnt_add = 1;
    #100
    $finish;
end

endmodule

iverilog_uart/uart_rx.vcd
$date
	Thu Jul 28 20:26:36 2022
$end
$version
	Icarus Verilog
$end
$timescale
	1ps
$end
$scope module tb_uart_rx $end
$var wire 1 ! cnt_end $end
$var reg 1 " clk $end
$var reg 1 # cnt_add $end
$var reg 1 $ rst_n $end
$scope module u_uart_rx $end
$var wire 1 " clk $end
$var wire 1 # cnt_add $end
$var wire 1 $ rst_n $end
$var wire 1 ! cnt_end $end
$scope function clogb2 $end
$var integer 32 % depth [31:0] $end
$upscope $end
$scope module u_counter $end
$var wire 1 " clk $end
$var wire 1 # cnt_add $end
$var wire 1 $ rst_n $end
$var wire 1 ! cnt_end $end
$var reg 3 & cnt [2:0] $end
$upscope $end
$upscope $end
$upscope $end
$enddefinitions $end
#0
$dumpvars
b0 &
bx %
0$
0#
0"
0!
$end
#5000
1"
#10000
0"
#15000
1"
#20000
0"
1#
1$
#25000
b1 &
1"
#30000
0"
#35000
b10 &
1"
#40000
0"
#45000
b11 &
1"
#50000
0"
#55000
1!
b100 &
1"
#60000
0"
#65000
0!
b0 &
1"
#70000
0"
#75000
b1 &
1"
#80000
0"
#85000
b10 &
1"
#90000
0"
#95000
b11 &
1"
#100000
0"
#105000
1!
b100 &
1"
#110000
0"
#115000
0!
b0 &
1"
