iverilog_uart/counter.v
module counter
#(parameter cnt_max=32)(
    clk,
    rst_n,
    cnt_add,
    cnt,
    cnt_end
);

/////////////////////////////////////////////////////////////////////////////////////
function integer clogb2 (
    input           integer depth
    );
begin
    if(depth == 0)
        clogb2  = 1;
    else if(depth != 0)
        for(clogb2  = 0; depth > 0;clogb2  = clogb2  + 1)
            depth = depth >> 1;
end
endfunction
localparam cnt_width = clogb2 (cnt_max);
////////////////////////////////////////////////////////////////////////////////////
    input clk     ;
    input rst_n   ;
    input cnt_add ;
    output reg [cnt_width-1:0] cnt ;
    output cnt_end;

always @(posedge clk or negedge rst_n) begin
    if (rst_n == 1'b0)
        cnt<=0;
    else if (cnt_add) 
                begin
                    if (cnt_end)
                        cnt<=0;
                    else
                        cnt<=cnt+1;
                end
end
assign cnt_end = cnt_add && cnt ==  cnt_max -1;
endmodule //counter

iverilog_uart/uart_tx.v
`include "counter.v"
module uart_tx #(parameter datawidth = 5 , Baudrate = 9600  )(
   input clk,
   input rst_n,
   input [datawidth-1:0] data_in,
   input tx_triger_flag,
   output txd

);
//////////////////////////////////////////////////////////////////////////////////////////////////////////////////////////
localparam  cnt_max1 = 50000000/Baudrate;
localparam  cnt_max2 = datawidth+2;
function integer clogb2 (
    input           integer depth
    );
begin
    if(depth == 0)
        clogb2  = 1;
    else if(depth != 0)
        for(clogb2  = 0; depth > 0;clogb2  = clogb2  + 1)
            depth = depth >> 1;
end
endfunction
localparam cnt_width1 = clogb2 (cnt_max1);
localparam cnt_width2 = clogb2 (cnt_max2);
//////////////////////////////////////////////////////////////////////////////////////////////////////////////////////////
reg tx_start_flag;
always @(posedge clk or negedge rst_n) begin
    if(!rst_n)begin
        tx_start_flag<=0;
    end
    else if (cnt_end2) begin
        tx_start_flag<=0;
    end
    else if (tx_triger_flag)begin
        tx_start_flag<=1;
    end
end
wire cnt_end1,cnt_end2;
wire [cnt_width1-1:0] cnt1;
wire [cnt_width2-1:0] cnt2;

counter #(
    .cnt_max ( cnt_max1 ))
 bitlenth_counter(
    .clk         ( clk         ),
    .rst_n       ( rst_n       ),
    .cnt_add     ( tx_start_flag ),
    .cnt         ( cnt1        ),
    .cnt_end     ( cnt_end1    )
);

counter #(
    .cnt_max ( cnt_max2 ))
 bitnum_counter(
    .clk         ( clk         ),
    .rst_n       ( rst_n       ),
    .cnt_add     ( cnt_end1    ),
    .cnt         ( cnt2        ),
    .cnt_end     ( cnt_end2    )
);

reg txd_reg;
always @(posedge clk ) begin
    if (tx_start_flag == 1)begin
        if (cnt2==0)
            txd_reg<=0;
        else if (cnt2==9)
            txd_reg<=1;
        else 
            txd_reg<=data_in[cnt2-1];
    end
    else begin
        txd_reg<=1;
    end
end
assign txd = txd_reg;
endmodule //uart_tx

iverilog_uart/tb_uart_tx.v
`timescale  1ns / 1ps
`include "uart_tx.v"
module tb_uart_tx;   

// uart_tx Parameters
parameter PERIOD  = 10;
parameter datawidth = 8;
parameter Baudrate =9600;

// uart_tx Inputs
reg   clk                                  = 0 ;
reg   rst_n                                = 0 ;
reg   [datawidth-1:0]  data_in             = 0 ;
reg   tx_triger_flag                       = 0 ;

// uart_tx Outputs
wire  txd                                  ;


initial
begin
    forever #(PERIOD/2)  clk=~clk;
end

initial
begin
    #(PERIOD*2) rst_n  =  1;
end

uart_tx#(
    .datawidth      ( datawidth ),
    .Baudrate   (Baudrate  )
)u_uart_tx(
    .clk            ( clk            ),
    .rst_n          ( rst_n          ),
    .data_in        ( data_in        ),
    .tx_triger_flag ( tx_triger_flag ),
    .txd            ( txd            )
);


initial
begin
    $dumpfile("uart_tx.vcd");
    $dumpvars    ;
    #20
    data_in=8'h70;
    tx_triger_flag=1;
    #10
    tx_triger_flag=0;
    #1000
    $finish;
end

endmodule

iverilog_uart/uart_tx.vcd
$date
	Fri Jul 29 11:50:16 2022
$end
$version
	Icarus Verilog
$end
$timescale
	1ps
$end
$scope module tb_uart_tx $end
$var wire 1 ! txd $end
$var reg 1 " clk $end
$var reg 8 # data_in [7:0] $end
$var reg 1 $ rst_n $end
$var reg 1 % tx_triger_flag $end
$scope module u_uart_tx $end
$var wire 1 " clk $end
$var wire 8 & data_in [7:0] $end
$var wire 1 $ rst_n $end
$var wire 1 % tx_triger_flag $end
$var wire 1 ! txd $end
$var wire 1 ' cnt_end2 $end
$var wire 1 ( cnt_end1 $end
$var wire 4 ) cnt2 [3:0] $end
$var wire 3 * cnt1 [2:0] $end
$var reg 1 + tx_start_flag $end
$var reg 1 , txd_reg $end
$scope function clogb2 $end
$var integer 32 - depth [31:0] $end
$upscope $end
$scope module bitlenth_counter $end
$var wire 1 " clk $end
$var wire 1 + cnt_add $end
$var wire 1 ( cnt_end $end
$var wire 1 $ rst_n $end
$var reg 3 . cnt [2:0] $end
$scope function clogb2 $end
$var integer 32 / depth [31:0] $end
$upscope $end
$upscope $end
$scope module bitnum_counter $end
$var wire 1 " clk $end
$var wire 1 ( cnt_add $end
$var wire 1 ' cnt_end $end
$var wire 1 $ rst_n $end
$var reg 4 0 cnt [3:0] $end
$scope function clogb2 $end
$var integer 32 1 depth [31:0] $end
$upscope $end
$upscope $end
$upscope $end
$upscope $end
$enddefinitions $end
#0
$dumpvars
bx 1
b0 0
bx /
b0 .
bx -
x,
0+
b0 *
b0 )
0(
0'
b0 &
0%
0$
b0 #
0"
x!
$end
#5000
1!
1,
1"
#10000
0"
#15000
1"
#20000
0"
1%
b1110000 #
b1110000 &
1$
#25000
1+
1"
#30000
0"
0%
#35000
b1 *
b1 .
0!
0,
1"
#40000
0"
#45000
b10 *
b10 .
1"
#50000
0"
#55000
b11 *
b11 .
1"
#60000
0"
#65000
1(
b100 *
b100 .
1"
#70000
0"
#75000
0(
b0 *
b0 .
b1 )
b1 0
1"
#80000
0"
#85000
b1 *
b1 .
1"
#90000
0"
#95000
b10 *
b10 .
1"
#100000
0"
#105000
b11 *
b11 .
1"
#110000
0"
#115000
1(
b100 *
b100 .
1"
#120000
0"
#125000
0(
b10 )
b10 0
b0 *
b0 .
1"
#130000
0"
#135000
b1 *
b1 .
1"
#140000
0"
#145000
b10 *
b10 .
1"
#150000
0"
#155000
b11 *
b11 .
1"
#160000
0"
#165000
1(
b100 *
b100 .
1"
#170000
0"
#175000
0(
b0 *
b0 .
b11 )
b11 0
1"
#180000
0"
#185000
b1 *
b1 .
1"
#190000
0"
#195000
b10 *
b10 .
1"
#200000
0"
#205000
b11 *
b11 .
1"
#210000
0"
#215000
1(
b100 *
b100 .
1"
#220000
0"
#225000
0(
b100 )
b100 0
b0 *
b0 .
1"
#230000
0"
#235000
b1 *
b1 .
1"
#240000
0"
#245000
b10 *
b10 .
1"
#250000
0"
#255000
b11 *
b11 .
1"
#260000
0"
#265000
1(
b100 *
b100 .
1"
#270000
0"
#275000
0(
b0 *
b0 .
b101 )
b101 0
1"
#280000
0"
#285000
b1 *
b1 .
1!
1,
1"
#290000
0"
#295000
b10 *
b10 .
1"
#300000
0"
#305000
b11 *
b11 .
1"
#310000
0"
#315000
1(
b100 *
b100 .
1"
#320000
0"
#325000
0(
b110 )
b110 0
b0 *
b0 .
1"
#330000
0"
#335000
b1 *
b1 .
1"
#340000
0"
#345000
b10 *
b10 .
1"
#350000
0"
#355000
b11 *
b11 .
1"
#360000
0"
#365000
1(
b100 *
b100 .
1"
#370000
0"
#375000
0(
b0 *
b0 .
b111 )
b111 0
1"
#380000
0"
#385000
b1 *
b1 .
1"
#390000
0"
#395000
b10 *
b10 .
1"
#400000
0"
#405000
b11 *
b11 .
1"
#410000
0"
#415000
1(
b100 *
b100 .
1"
#420000
0"
#425000
0(
b1000 )
b1000 0
b0 *
b0 .
1"
#430000
0"
#435000
b1 *
b1 .
0!
0,
1"
#440000
0"
#445000
b10 *
b10 .
1"
#450000
0"
#455000
b11 *
b11 .
1"
#460000
0"
#465000
1(
b100 *
b100 .
1"
#470000
0"
#475000
0(
0'
b0 *
b0 .
b1001 )
b1001 0
1"
#480000
0"
#485000
b1 *
b1 .
1!
1,
1"
#490000
0"
#495000
b10 *
b10 .
1"
#500000
0"
#505000
b11 *
b11 .
1"
#510000
0"
#515000
1'
1(
b100 *
b100 .
1"
#520000
0"
#525000
0'
0(
0+
b0 )
b0 0
b0 *
b0 .
1"
